yamada/H_polynomial.py
yamada/__init__.py
yamada/spatial_graph_diagrams.py
yamada/spatial_graph_enumeration.py
yamada/spatial_graphs.py
yamada/utilities.py
yamada/visualization.py
Yamada-0.2.2.dist-info/LICENSE.txt
Yamada-0.2.2.dist-info/METADATA
Yamada-0.2.2.dist-info/WHEEL
Yamada-0.2.2.dist-info/top_level.txt
Yamada-0.2.2.dist-info/RECORD
