Metadata-Version: 2.1
Name: Yamada
Version: 0.2.2
Summary: Calculate the Yamada polynomial of spatial topologies.
Author-email: Chad Peterson <cp44@illinois.edu>, Nathan Dunfield <nmd@illinois.edu>
Project-URL: Homepage, https://github.com/Chad-Peterson/Yamada
Project-URL: Bug Tracker, https://github.com/Chad-Peterson/Yamada/issues
Classifier: Programming Language :: Python :: 3
Classifier: License :: OSI Approved :: MIT License
Classifier: Operating System :: OS Independent
Requires-Python: >=3.9
License-File: LICENSE.txt
Requires-Dist: networkx (~=2.8.5)
Requires-Dist: matplotlib
Requires-Dist: numpy
Requires-Dist: cypari (~=2.4.1)
Requires-Dist: jupyter
Requires-Dist: nbconvert
Requires-Dist: numba
Provides-Extra: doc
Requires-Dist: sphinx ; extra == 'doc'
Provides-Extra: test
Requires-Dist: pytest ; extra == 'test'
